env_logger/__init__.py
env_logger/_handlers.py
env_logger/py.typed
env_logger-0.4.1.dist-info/LICENSE
env_logger-0.4.1.dist-info/METADATA
env_logger-0.4.1.dist-info/WHEEL
env_logger-0.4.1.dist-info/entry_points.txt
env_logger-0.4.1.dist-info/RECORD
