Metadata-Version: 2.1
Name: env_logger
Version: 0.4.1
Summary: The easy way to configure logging
Home-page: https://github.com/apljungquist/env_logger_py
License: MIT
Author: AP Ljungquist
Author-email: ap@ljungquist.eu
Requires-Python: >=3.8,<4.0
Classifier: License :: OSI Approved :: MIT License
Classifier: Programming Language :: Python :: 3
Classifier: Programming Language :: Python :: 3.8
Classifier: Programming Language :: Python :: 3.9
Classifier: Programming Language :: Python :: 3.10
Classifier: Programming Language :: Python :: 3.11
Classifier: Programming Language :: Python :: 3.12
Requires-Dist: colorama (>=0.4.6,<0.5.0)
